awslabs/__init__.py
awslabs/mcp_bedrock_kb_retrieval_expert/__init__.py
awslabs/mcp_bedrock_kb_retrieval_expert/models.py
awslabs/mcp_bedrock_kb_retrieval_expert/server.py
awslabs/mcp_bedrock_kb_retrieval_expert/knowledgebases/__init__.py
awslabs/mcp_bedrock_kb_retrieval_expert/knowledgebases/clients.py
awslabs/mcp_bedrock_kb_retrieval_expert/knowledgebases/discovery.py
awslabs/mcp_bedrock_kb_retrieval_expert/knowledgebases/runtime.py
awslabs_mcp_bedrock_kb_retrieval_expert-0.0.311803.dist-info/METADATA
awslabs_mcp_bedrock_kb_retrieval_expert-0.0.311803.dist-info/WHEEL
awslabs_mcp_bedrock_kb_retrieval_expert-0.0.311803.dist-info/entry_points.txt
awslabs_mcp_bedrock_kb_retrieval_expert-0.0.311803.dist-info/RECORD
