Metadata-Version: 2.4
Name: awslabs.mcp-bedrock-kb-retrieval-expert
Version: 0.0.311803
Summary: An AWS Labs Model Context Protocol (MCP) server bedrock-kb-retrieval expert
Requires-Python: >=3.13
Requires-Dist: boto3>=1.37.23
Requires-Dist: loguru>=0.7.3
Requires-Dist: mcp[cli]>=1.6.0
Requires-Dist: pydantic>=2.11.1
